Metadata-Version: 2.1
Name: proba-distr
Version: 0.1
Summary: Gaussian and Binomial probability distributions package for Python
Home-page: UNKNOWN
Author: Marina Villaschi
Author-email: marinavillaschi@gmail.com
License: UNKNOWN
Platform: UNKNOWN
